<?xml version="1.0" encoding="UTF-8"?>
<objects serializationModel="Studio.02.01.00">
	<object class="AudioFile" id="{9cdaadaa-1fb7-4700-b6f1-dc30574a40f4}">
		<property name="assetPath">
			<value>takedamage_4.wav</value>
		</property>
		<property name="frequencyInKHz">
			<value>44.0999985</value>
		</property>
		<property name="channelCount">
			<value>1</value>
		</property>
		<property name="length">
			<value>0.25</value>
		</property>
		<relationship name="masterAssetFolder">
			<destination>{0fd0ab72-e73f-4a55-9230-406f3e709eea}</destination>
		</relationship>
	</object>
</objects>
